permasigner/__init__.py
permasigner/__main__.py
permasigner/__version__.py
permasigner/copy.py
permasigner/dpkg.py
permasigner/installer.py
permasigner/logger.py
permasigner/permasigner.py
permasigner/sign.py
permasigner/tcprelay.py
permasigner/utils.py
permasigner/bundled/__init__.py
permasigner/bundled/constrictor/__init__.py
permasigner/bundled/constrictor/ar.py
permasigner/bundled/constrictor/dpkg.py
permasigner/bundled/unix_ar/__init__.py
permasigner/bundled/unix_ar/unix_ar.py
permasigner/data/certificate.p12
permasigner/data/entitlements.plist
permasigner/data/DEBIAN/control
permasigner/data/DEBIAN/postinst
permasigner/data/DEBIAN/prerm
permasigner-1.1.3.dist-info/LICENSE
permasigner-1.1.3.dist-info/METADATA
permasigner-1.1.3.dist-info/WHEEL
permasigner-1.1.3.dist-info/entry_points.txt
permasigner-1.1.3.dist-info/top_level.txt
permasigner-1.1.3.dist-info/zip-safe
permasigner-1.1.3.dist-info/RECORD
