Metadata-Version: 2.1
Name: permasigner
Version: 1.1.3
Summary: Permanently signs IPAs on jailbroken iDevices (persists on stock).
Home-page: https://github.com/permasigner/permasigner
Author: Nebula
Author-email: me@itsnebula.net
License: BSD-3-Clause
Keywords: python,windows,macos,linux,docker,cli,open-source,ios,command-line-app,cli-app,hacktoberfest,procursus,permasign,permasigner
Classifier: Natural Language :: English
Classifier: Environment :: Console
Classifier: Operating System :: OS Independent
Requires-Python: >=3.7
License-File: LICENSE
Requires-Dist: requests (==2.28.1)
Requires-Dist: toml (==0.10.2)
Requires-Dist: urllib3 (==1.26.12)
Requires-Dist: pycodestyle (==2.9.1)
Requires-Dist: idna (==3.3)
Requires-Dist: charset-normalizer (==2.1.1)
Requires-Dist: certifi (==2022.6.15)
Requires-Dist: autopep8 (==1.7.0)
Requires-Dist: scp (==0.14.4) ; sys_platform == "linux" or sys_platform == "win32" or "freebsd" in sys_platform or (sys_platform == "darwin" and platform_machine == "x86_64") or (sys_platform == "darwin" and platform_machine == "arm64")
Requires-Dist: six (==1.16.0) ; sys_platform == "linux" or sys_platform == "win32" or "freebsd" in sys_platform or (sys_platform == "darwin" and platform_machine == "x86_64") or (sys_platform == "darwin" and platform_machine == "arm64")
Requires-Dist: bcrypt (==4.0.0) ; sys_platform == "linux" or sys_platform == "win32" or "freebsd" in sys_platform or (sys_platform == "darwin" and platform_machine == "x86_64") or (sys_platform == "darwin" and platform_machine == "arm64")
Requires-Dist: cffi (==1.15.1) ; sys_platform == "linux" or sys_platform == "win32" or "freebsd" in sys_platform or (sys_platform == "darwin" and platform_machine == "x86_64") or (sys_platform == "darwin" and platform_machine == "arm64")
Requires-Dist: cryptography (==37.0.4) ; sys_platform == "linux" or sys_platform == "win32" or "freebsd" in sys_platform or (sys_platform == "darwin" and platform_machine == "x86_64") or (sys_platform == "darwin" and platform_machine == "arm64")
Requires-Dist: paramiko (==2.11.0) ; sys_platform == "linux" or sys_platform == "win32" or "freebsd" in sys_platform or (sys_platform == "darwin" and platform_machine == "x86_64") or (sys_platform == "darwin" and platform_machine == "arm64")
Requires-Dist: pycparser (==2.21) ; sys_platform == "linux" or sys_platform == "win32" or "freebsd" in sys_platform or (sys_platform == "darwin" and platform_machine == "x86_64") or (sys_platform == "darwin" and platform_machine == "arm64")
Requires-Dist: PyNaCl (==1.5.0) ; sys_platform == "linux" or sys_platform == "win32" or "freebsd" in sys_platform or (sys_platform == "darwin" and platform_machine == "x86_64") or (sys_platform == "darwin" and platform_machine == "arm64")
